amulet/game/__init__.py
amulet/game/__init__.pyi
amulet/game/_amulet_game.cp311-win_amd64.pyd
amulet/game/_amulet_game.pyi
amulet/game/_version.py
amulet/game/amulet_game.dll
amulet/game/amulet_game.lib
amulet/game/amulet_gameConfig.cmake
amulet/game/dll.hpp
amulet/game/game.hpp
amulet/game/game.py
amulet/game/py.typed
amulet/game/versions.pkl.gz
amulet/game/__pycache__/__init__.cpython-311.pyc
amulet/game/__pycache__/_version.cpython-311.pyc
amulet/game/__pycache__/game.cpython-311.pyc
amulet/game/__pyinstaller/__init__.py
amulet/game/__pyinstaller/hook-amulet.game.py
amulet/game/abc/__init__.py
amulet/game/abc/__init__.pyi
amulet/game/abc/_block_specification.py
amulet/game/abc/biome.hpp
amulet/game/abc/biome.py
amulet/game/abc/block.hpp
amulet/game/abc/block.py
amulet/game/abc/game_version_container.py
amulet/game/abc/json_interface.py
amulet/game/abc/version.hpp
amulet/game/abc/version.py
amulet/game/abc/__pycache__/__init__.cpython-311.pyc
amulet/game/abc/__pycache__/_block_specification.cpython-311.pyc
amulet/game/abc/__pycache__/biome.cpython-311.pyc
amulet/game/abc/__pycache__/block.cpython-311.pyc
amulet/game/abc/__pycache__/game_version_container.cpython-311.pyc
amulet/game/abc/__pycache__/json_interface.cpython-311.pyc
amulet/game/abc/__pycache__/version.cpython-311.pyc
amulet/game/bedrock/__init__.py
amulet/game/bedrock/__init__.pyi
amulet/game/bedrock/_biome.py
amulet/game/bedrock/_block.py
amulet/game/bedrock/_version.py
amulet/game/bedrock/__pycache__/__init__.cpython-311.pyc
amulet/game/bedrock/__pycache__/_biome.cpython-311.pyc
amulet/game/bedrock/__pycache__/_block.cpython-311.pyc
amulet/game/bedrock/__pycache__/_version.cpython-311.pyc
amulet/game/java/__init__.pyi
amulet/game/java/_block.pyi
amulet/game/java/biome.py
amulet/game/java/block.hpp
amulet/game/java/block.py
amulet/game/java/version.hpp
amulet/game/java/version.py
amulet/game/java/__pycache__/biome.cpython-311.pyc
amulet/game/java/__pycache__/block.cpython-311.pyc
amulet_game-1.0.4a0.dist-info/METADATA
amulet_game-1.0.4a0.dist-info/WHEEL
amulet_game-1.0.4a0.dist-info/entry_points.txt
amulet_game-1.0.4a0.dist-info/top_level.txt
amulet_game-1.0.4a0.dist-info/RECORD
